Metadata-Version: 1.1
Name: rpconnect
Version: 0.9.2
Summary: lightweight rpc framework
Home-page: https://github.com/MaineKuehn/rpconnect
Author: Eileen Kuehn, Max Fischer
Author-email: maxfischer2781@gmail.com
License: MIT
Keywords: rpc remote-call
Platform: UNKNOWN
Classifier: Development Status :: 4 - Beta
Classifier: License :: OSI Approved :: MIT License
Classifier: Intended Audience :: Education
Classifier: Topic :: Education
Classifier: Programming Language :: Python :: 3 :: Only
